Metadata-Version: 2.1
Name: FeatureSelector
Version: 0.0
Summary: Package used to implement diverse feature selection methods
Home-page: UNKNOWN
Author-email: tobiasrossimuller@gmail.com
License: UNKNOWN
Platform: UNKNOWN
